mcp_pytest_runner/__init__.py
mcp_pytest_runner/domain.py
mcp_pytest_runner/main.py
mcp_pytest_runner/py.typed
mcp_pytest_runner-0.2.1.dist-info/METADATA
mcp_pytest_runner-0.2.1.dist-info/WHEEL
mcp_pytest_runner-0.2.1.dist-info/entry_points.txt
mcp_pytest_runner-0.2.1.dist-info/RECORD
